{
  "snapshots": [
    {
      "timestamp": "2026-02-27T18:52:44.375130Z",
      "vedolo_holders": 10972,
      "dolo_locked": 54045276.83,
      "vote_weight": 34877554.8595,
      "exercised_usd": 1901061.93,
      "exercised_txs": 3023,
      "tvl": 289192688,
      "volume_24h": 2999864.0897943685
    },
    {
      "timestamp": "2026-02-28T02:09:21.032454Z",
      "vedolo_holders": 10972,
      "dolo_locked": 54035277.12,
      "vote_weight": 34855410.6942,
      "exercised_usd": 1901061.93,
      "exercised_txs": 3023,
      "tvl": 287437150,
      "volume_24h": 2823363.3588527753
    },
    {
      "timestamp": "2026-02-28T06:51:51.114177Z",
      "vedolo_holders": 10972,
      "dolo_locked": 54035277.12,
      "vote_weight": 34841432.5058,
      "exercised_usd": 1902013.9,
      "exercised_txs": 3037,
      "tvl": 285384584,
      "volume_24h": 3324149.1573134083
    },
    {
      "timestamp": "2026-02-28T12:52:17.787574Z",
      "vedolo_holders": 10972,
      "dolo_locked": 54064817.88,
      "vote_weight": 34852826.3579,
      "exercised_usd": 1902013.9,
      "exercised_txs": 3037,
      "tvl": 287546395,
      "volume_24h": 3163829.5924301352
    },
    {
      "timestamp": "2026-02-28T18:45:00.930381Z",
      "vedolo_holders": 10971,
      "dolo_locked": 54077650.33,
      "vote_weight": 34848044.8322,
      "exercised_usd": 1902013.9,
      "exercised_txs": 3037,
      "tvl": 282569480,
      "volume_24h": 6056320.682253949
    },
    {
      "timestamp": "2026-03-01T02:24:43.608407Z",
      "vedolo_holders": 10971,
      "dolo_locked": 54084115.02,
      "vote_weight": 34830996.0491,
      "exercised_usd": 1902013.9,
      "exercised_txs": 3037,
      "tvl": 287908640,
      "volume_24h": 6255817.377465689
    },
    {
      "timestamp": "2026-03-01T07:01:57.797559Z",
      "vedolo_holders": 10972,
      "dolo_locked": 54085975.84,
      "vote_weight": 34818037.016,
      "exercised_usd": 1903044.6,
      "exercised_txs": 3051,
      "tvl": 293399112,
      "volume_24h": 6279559.136761799
    },
    {
      "timestamp": "2026-03-01T12:56:21.716594Z",
      "vedolo_holders": 10972,
      "dolo_locked": 54085976.93,
      "vote_weight": 34799909.9123,
      "exercised_usd": 1903044.6,
      "exercised_txs": 3051,
      "tvl": 313353422,
      "volume_24h": 5971743.112337996
    },
    {
      "timestamp": "2026-03-01T18:43:48.046509Z",
      "vedolo_holders": 10973,
      "dolo_locked": 54086387.92,
      "vote_weight": 34782520.4705,
      "exercised_usd": 1903044.6,
      "exercised_txs": 3051,
      "tvl": 293202160,
      "volume_24h": 3523114.3903199886
    }
  ]
}