{
  "snapshots": [
    {
      "timestamp": "2026-04-10T13:25:52.083863Z",
      "vedolo_holders": 10964,
      "dolo_locked": 54377546.2,
      "vote_weight": 32754337.1407,
      "exercised_usd": 1926760.28,
      "exercised_txs": 3415,
      "tvl": 865984118,
      "volume_24h": 2840815.4620358986
    },
    {
      "timestamp": "2026-04-10T19:08:29.012590Z",
      "vedolo_holders": 10964,
      "dolo_locked": 54377047.06,
      "vote_weight": 32740499.6119,
      "exercised_usd": 1926955.27,
      "exercised_txs": 3417,
      "tvl": 451417510,
      "volume_24h": 3325906.54882508
    }
  ]
}