{"version":2,"chain":"ethereum","address":"0x014ccc93ff00d407bc7ff533d5c3b32aa3597f44","snapshotDate":"2026-05-04","generatedAt":"2026-05-04T04:19:14.919882Z","summary":{"verified":0,"pre_snapshot_carry":0,"mismatch":1,"no_netflow":0,"no_snapshot":3,"unavailable":0},"strictSummary":{"verified":0,"inferred":0,"mismatch":1,"coverage_incomplete":3,"unavailable":0},"canonicalHistory":{"coverageStatus":"fresh","lastScannedBlock":25018310,"comparisonBlock":25016636,"freshForNetflowComparison":true},"markets":{"0":{"token":"","symbol":"UNK","decimals":18,"cumulativeYield":"0","status":"no_snapshot","method":"insufficient-history","strictStatus":"coverage_incomplete","strictMethod":"insufficient-history","strictReason":"snapshot_missing_market","firstDate":"","firstPar":"0","firstWei":"0","lastDate":"","lastPar":"0","lastWei":"0","days":0,"isLatestSnapshot":false,"hasStaticParWindow":false,"canonicalHistoryCoverageStatus":"fresh","canonicalHistoryLastScannedBlock":25018310,"canonicalHistoryComparisonBlock":25016636,"canonicalHistoryConsistencyStatus":"mismatch","canonicalHistoryTotalDeltaWei":"-6457996","canonicalHistoryAccountCount":2,"canonicalHistoryEventCount":4,"canonicalHistoryHasBorrowAccount":false,"canonicalHistoryHasLegacyUnknownAccount":false,"canonicalHistoryNetflowDiffWei":"-114952496041307068408"},"2":{"token":"","symbol":"UNK","decimals":18,"cumulativeYield":"0","status":"no_snapshot","method":"insufficient-history","strictStatus":"coverage_incomplete","strictMethod":"insufficient-history","strictReason":"snapshot_missing_market","firstDate":"","firstPar":"0","firstWei":"0","lastDate":"","lastPar":"0","lastWei":"0","days":0,"isLatestSnapshot":false,"hasStaticParWindow":false,"canonicalHistoryCoverageStatus":"fresh","canonicalHistoryLastScannedBlock":25018310,"canonicalHistoryComparisonBlock":25016636,"canonicalHistoryConsistencyStatus":"mismatch","canonicalHistoryTotalDeltaWei":"436869","canonicalHistoryAccountCount":5,"canonicalHistoryEventCount":13,"canonicalHistoryHasBorrowAccount":false,"canonicalHistoryHasLegacyUnknownAccount":false,"canonicalHistoryNetflowDiffWei":"-66172311"},"5":{"token":"","symbol":"UNK","decimals":18,"cumulativeYield":"0","status":"no_snapshot","method":"insufficient-history","strictStatus":"coverage_incomplete","strictMethod":"insufficient-history","strictReason":"snapshot_missing_market","firstDate":"","firstPar":"0","firstWei":"0","lastDate":"","lastPar":"0","lastWei":"0","days":0,"isLatestSnapshot":false,"hasStaticParWindow":false,"canonicalHistoryCoverageStatus":"fresh","canonicalHistoryLastScannedBlock":25018310,"canonicalHistoryComparisonBlock":25016636,"canonicalHistoryConsistencyStatus":"mismatch","canonicalHistoryTotalDeltaWei":"-78","canonicalHistoryAccountCount":2,"canonicalHistoryEventCount":4,"canonicalHistoryHasBorrowAccount":false,"canonicalHistoryHasLegacyUnknownAccount":false,"canonicalHistoryNetflowDiffWei":"-197249971"},"10":{"token":"0x738d1115b90efa71ae468f1287fc864775e23a31","symbol":"srUSD","decimals":18,"cumulativeYield":"0","status":"mismatch","method":"snapshot-fallback","strictStatus":"mismatch","strictMethod":"canonical-history-mismatch","strictReason":"canonical_history_mismatch","firstDate":"2026-01-20","firstPar":"50216679989033151626","firstWei":"50216679989033151626","lastDate":"2026-01-23","lastPar":"50216679989033151626","lastWei":"50216679989033151626","days":4,"isLatestSnapshot":false,"hasStaticParWindow":true,"canonicalHistoryCoverageStatus":"fresh","canonicalHistoryLastScannedBlock":25018310,"canonicalHistoryComparisonBlock":25016636,"canonicalHistoryConsistencyStatus":"mismatch","canonicalHistoryTotalDeltaWei":"0","canonicalHistoryAccountCount":7,"canonicalHistoryEventCount":22,"canonicalHistoryHasBorrowAccount":false,"canonicalHistoryHasLegacyUnknownAccount":false,"snapshotYield":"0","netflowYield":"-1815282425931337558677","diff":"-1815282425931337558677","canonicalHistoryNetflowDiffWei":"-1865499105920370710303"}}}