{"version":2,"chain":"ethereum","address":"0x20293652c2975e3b21b367901d55913b0f292a20","snapshotDate":"2026-05-06","generatedAt":"2026-05-06T15:16:03.874375Z","summary":{"verified":0,"pre_snapshot_carry":1,"mismatch":0,"no_netflow":0,"no_snapshot":0,"unavailable":0},"strictSummary":{"verified":0,"inferred":1,"mismatch":0,"coverage_incomplete":0,"unavailable":0},"canonicalHistory":{"coverageStatus":"fresh","lastScannedBlock":25035941,"comparisonBlock":25035008,"freshForNetflowComparison":true},"markets":{"2":{"token":"0xa0b86991c6218b36c1d19d4a2e9eb0ce3606eb48","symbol":"USDC","decimals":6,"cumulativeYield":"5216355","status":"pre_snapshot_carry","method":"netflow+pre-snapshot-carry","strictStatus":"inferred","strictMethod":"netflow+pre-snapshot-carry","strictReason":"pre_snapshot_carry_requires_inference","firstDate":"2026-05-01","firstPar":"8455708457","firstWei":"8764963724","lastDate":"2026-05-06","lastPar":"8455708457","lastWei":"8769288148","days":6,"isLatestSnapshot":true,"hasStaticParWindow":true,"canonicalHistoryCoverageStatus":"fresh","canonicalHistoryLastScannedBlock":25035941,"canonicalHistoryComparisonBlock":25035008,"canonicalHistoryConsistencyStatus":"match","canonicalHistoryTotalDeltaWei":"8764071793","canonicalHistoryAccountCount":1,"canonicalHistoryEventCount":1,"canonicalHistoryHasBorrowAccount":false,"canonicalHistoryHasLegacyUnknownAccount":false,"snapshotYield":"4324424","netflowYield":"5216355","diff":"891931","canonicalHistoryNetflowDiffWei":"0","verificationBaseline":"all-time-netflow","preSnapshotCarryYield":"891931","preSnapshotCarryResidual":"0","preSnapshotCarryWindowType":"exact_post_snapshot_window"}}}