{"version":2,"chain":"ethereum","address":"0x492d806aeb9dbfe07454842830e5849eeb76d161","snapshotDate":"2026-05-07","generatedAt":"2026-05-07T20:04:31.498820Z","summary":{"verified":0,"pre_snapshot_carry":0,"mismatch":2,"no_netflow":0,"no_snapshot":1,"unavailable":0},"strictSummary":{"verified":0,"inferred":0,"mismatch":2,"coverage_incomplete":1,"unavailable":0},"canonicalHistory":{"coverageStatus":"fresh","lastScannedBlock":25044885,"comparisonBlock":25044012,"freshForNetflowComparison":true},"markets":{"0":{"token":"","symbol":"UNK","decimals":18,"cumulativeYield":"0","status":"no_snapshot","method":"insufficient-history","strictStatus":"coverage_incomplete","strictMethod":"insufficient-history","strictReason":"snapshot_missing_market","firstDate":"","firstPar":"0","firstWei":"0","lastDate":"","lastPar":"0","lastWei":"0","days":0,"isLatestSnapshot":false,"hasStaticParWindow":false,"canonicalHistoryCoverageStatus":"fresh","canonicalHistoryLastScannedBlock":25044885,"canonicalHistoryComparisonBlock":25044012,"canonicalHistoryConsistencyStatus":"netflow_only","canonicalHistoryTotalDeltaWei":"0","canonicalHistoryAccountCount":0,"canonicalHistoryEventCount":0,"canonicalHistoryHasBorrowAccount":false,"canonicalHistoryHasLegacyUnknownAccount":false,"canonicalHistoryNetflowDiffWei":"-3653052877155220"},"1":{"token":"0x8d0d000ee44948fc98c9b98a4fa4921476f08b0d","symbol":"USD1","decimals":18,"cumulativeYield":"146377011459","status":"mismatch","method":"snapshot-fallback","strictStatus":"mismatch","strictMethod":"canonical-history-mismatch","strictReason":"canonical_history_mismatch","firstDate":"2026-02-07","firstPar":"186563653542601","firstWei":"190237760680579","lastDate":"2026-02-18","lastPar":"186563653542601","lastWei":"190384137692038","days":12,"isLatestSnapshot":false,"hasStaticParWindow":true,"canonicalHistoryCoverageStatus":"fresh","canonicalHistoryLastScannedBlock":25044885,"canonicalHistoryComparisonBlock":25044012,"canonicalHistoryConsistencyStatus":"mismatch","canonicalHistoryTotalDeltaWei":"-176780756469620400601","canonicalHistoryAccountCount":2,"canonicalHistoryEventCount":41,"canonicalHistoryHasBorrowAccount":false,"canonicalHistoryHasLegacyUnknownAccount":false,"snapshotYield":"146377011459","netflowYield":"-118873446161650070647891","diff":"-118873446161796447659350","canonicalHistoryNetflowDiffWei":"-119050227108503828740530"},"5":{"token":"0xdac17f958d2ee523a2206206994597c13d831ec7","symbol":"USDT","decimals":6,"cumulativeYield":"2","status":"mismatch","method":"snapshot-fallback","strictStatus":"mismatch","strictMethod":"canonical-history-mismatch","strictReason":"canonical_history_mismatch","firstDate":"2026-04-15","firstPar":"487","firstWei":"511","lastDate":"2026-05-07","lastPar":"487","lastWei":"513","days":23,"isLatestSnapshot":true,"hasStaticParWindow":true,"canonicalHistoryCoverageStatus":"fresh","canonicalHistoryLastScannedBlock":25044885,"canonicalHistoryComparisonBlock":25044012,"canonicalHistoryConsistencyStatus":"mismatch","canonicalHistoryTotalDeltaWei":"353979228","canonicalHistoryAccountCount":2,"canonicalHistoryEventCount":33,"canonicalHistoryHasBorrowAccount":false,"canonicalHistoryHasLegacyUnknownAccount":false,"snapshotYield":"2","netflowYield":"-353980623","diff":"-353980625","canonicalHistoryNetflowDiffWei":"-1908"}}}