{"version":2,"chain":"ethereum","address":"0x4f0f7e45405ef9a0b2d347a57f6cb7061c46912a","snapshotDate":"2026-05-07","generatedAt":"2026-05-07T23:34:19.474131Z","summary":{"verified":0,"pre_snapshot_carry":1,"mismatch":3,"no_netflow":0,"no_snapshot":1,"unavailable":0},"strictSummary":{"verified":0,"inferred":0,"mismatch":4,"coverage_incomplete":1,"unavailable":0},"canonicalHistory":{"coverageStatus":"fresh","lastScannedBlock":25046474,"comparisonBlock":25045441,"freshForNetflowComparison":true},"markets":{"0":{"token":"0xc02aaa39b223fe8d0a0e5c4f27ead9083c756cc2","symbol":"WETH","decimals":18,"cumulativeYield":"7749331226997818198","status":"pre_snapshot_carry","method":"netflow+pre-snapshot-carry","strictStatus":"mismatch","strictMethod":"canonical-history-mismatch","strictReason":"canonical_history_mismatch","firstDate":"2026-01-20","firstPar":"146617741262503","firstWei":"147271763251369","lastDate":"2026-05-07","lastPar":"146617741262503","lastWei":"147529555743868","days":108,"isLatestSnapshot":true,"hasStaticParWindow":true,"canonicalHistoryCoverageStatus":"fresh","canonicalHistoryLastScannedBlock":25046474,"canonicalHistoryComparisonBlock":25045441,"canonicalHistoryConsistencyStatus":"mismatch","canonicalHistoryTotalDeltaWei":"4914168923604633","canonicalHistoryAccountCount":5,"canonicalHistoryEventCount":15,"canonicalHistoryHasBorrowAccount":false,"canonicalHistoryHasLegacyUnknownAccount":false,"snapshotYield":"257792492499","netflowYield":"7749331226997818198","diff":"7749330969205325699","canonicalHistoryNetflowDiffWei":"7754097866365678963","verificationBaseline":"all-time-netflow","preSnapshotCarryYield":"7749330969205325699","preSnapshotCarryResidual":"0","preSnapshotCarryWindowType":"exact_post_snapshot_window"},"1":{"token":"0x8d0d000ee44948fc98c9b98a4fa4921476f08b0d","symbol":"USD1","decimals":18,"cumulativeYield":"27976936563845541705","status":"mismatch","method":"snapshot-fallback","strictStatus":"mismatch","strictMethod":"canonical-history-mismatch","strictReason":"canonical_history_mismatch","firstDate":"2026-04-21","firstPar":"66371065396193524621620","firstWei":"68142245073420785401074","lastDate":"2026-05-07","lastPar":"6854602730999414","lastWei":"7049668739833116","days":17,"isLatestSnapshot":true,"hasStaticParWindow":false,"canonicalHistoryCoverageStatus":"fresh","canonicalHistoryLastScannedBlock":25046474,"canonicalHistoryComparisonBlock":25045441,"canonicalHistoryConsistencyStatus":"mismatch","canonicalHistoryTotalDeltaWei":"-57995044449169447502","canonicalHistoryAccountCount":6,"canonicalHistoryEventCount":21,"canonicalHistoryHasBorrowAccount":false,"canonicalHistoryHasLegacyUnknownAccount":false,"snapshotYield":"27976936563845541705","netflowYield":"-9851663763607376269798","diff":"-9879640700171221811503","canonicalHistoryNetflowDiffWei":"-9909665857725285550416"},"2":{"token":"0xa0b86991c6218b36c1d19d4a2e9eb0ce3606eb48","symbol":"USDC","decimals":6,"cumulativeYield":"13","status":"mismatch","method":"snapshot-fallback","strictStatus":"mismatch","strictMethod":"canonical-history-mismatch","strictReason":"canonical_history_mismatch","firstDate":"2026-01-20","firstPar":"1587","firstWei":"1624","lastDate":"2026-05-07","lastPar":"321","lastWei":"332","days":108,"isLatestSnapshot":true,"hasStaticParWindow":false,"canonicalHistoryCoverageStatus":"fresh","canonicalHistoryLastScannedBlock":25046474,"canonicalHistoryComparisonBlock":25045441,"canonicalHistoryConsistencyStatus":"mismatch","canonicalHistoryTotalDeltaWei":"-40039702","canonicalHistoryAccountCount":6,"canonicalHistoryEventCount":21,"canonicalHistoryHasBorrowAccount":false,"canonicalHistoryHasLegacyUnknownAccount":false,"snapshotYield":"13","netflowYield":"-730590858371","diff":"-730590858384","canonicalHistoryNetflowDiffWei":"-730630898405"},"4":{"token":"","symbol":"UNK","decimals":18,"cumulativeYield":"0","status":"no_snapshot","method":"insufficient-history","strictStatus":"coverage_incomplete","strictMethod":"insufficient-history","strictReason":"snapshot_missing_market","firstDate":"","firstPar":"0","firstWei":"0","lastDate":"","lastPar":"0","lastWei":"0","days":0,"isLatestSnapshot":false,"hasStaticParWindow":false,"canonicalHistoryCoverageStatus":"fresh","canonicalHistoryLastScannedBlock":25046474,"canonicalHistoryComparisonBlock":25045441,"canonicalHistoryConsistencyStatus":"mismatch","canonicalHistoryTotalDeltaWei":"4582","canonicalHistoryAccountCount":3,"canonicalHistoryEventCount":14,"canonicalHistoryHasBorrowAccount":false,"canonicalHistoryHasLegacyUnknownAccount":false,"canonicalHistoryNetflowDiffWei":"367257537"},"5":{"token":"0xdac17f958d2ee523a2206206994597c13d831ec7","symbol":"USDT","decimals":6,"cumulativeYield":"11671186","status":"mismatch","method":"snapshot-fallback","strictStatus":"mismatch","strictMethod":"snapshot-fallback","strictReason":"snapshot_netflow_mismatch","firstDate":"2026-04-24","firstPar":"51183642333","firstWei":"53820384254","lastDate":"2026-04-25","lastPar":"46429612404","lastWei":"48832036078","days":2,"isLatestSnapshot":false,"hasStaticParWindow":false,"canonicalHistoryCoverageStatus":"fresh","canonicalHistoryLastScannedBlock":25046474,"canonicalHistoryComparisonBlock":25045441,"canonicalHistoryConsistencyStatus":"match","canonicalHistoryTotalDeltaWei":"-18881919","canonicalHistoryAccountCount":3,"canonicalHistoryEventCount":16,"canonicalHistoryHasBorrowAccount":false,"canonicalHistoryHasLegacyUnknownAccount":false,"snapshotYield":"11671186","netflowYield":"48850917997","diff":"48839246811","canonicalHistoryNetflowDiffWei":"0"}}}