{"version":2,"chain":"ethereum","address":"0x54b4ab76d7c9977428935eae6fe68cb5802ab0a1","snapshotDate":"2026-05-07","generatedAt":"2026-05-07T09:17:55.855106Z","summary":{"verified":0,"pre_snapshot_carry":0,"mismatch":1,"no_netflow":0,"no_snapshot":2,"unavailable":0},"strictSummary":{"verified":0,"inferred":0,"mismatch":1,"coverage_incomplete":2,"unavailable":0},"canonicalHistory":{"coverageStatus":"fresh","lastScannedBlock":25041854,"comparisonBlock":25040757,"freshForNetflowComparison":true},"markets":{"0":{"token":"","symbol":"UNK","decimals":18,"cumulativeYield":"0","status":"no_snapshot","method":"insufficient-history","strictStatus":"coverage_incomplete","strictMethod":"insufficient-history","strictReason":"snapshot_missing_market","firstDate":"","firstPar":"0","firstWei":"0","lastDate":"","lastPar":"0","lastWei":"0","days":0,"isLatestSnapshot":false,"hasStaticParWindow":false,"canonicalHistoryCoverageStatus":"fresh","canonicalHistoryLastScannedBlock":25041854,"canonicalHistoryComparisonBlock":25040757,"canonicalHistoryConsistencyStatus":"netflow_only","canonicalHistoryTotalDeltaWei":"0","canonicalHistoryAccountCount":0,"canonicalHistoryEventCount":0,"canonicalHistoryHasBorrowAccount":false,"canonicalHistoryHasLegacyUnknownAccount":false,"canonicalHistoryNetflowDiffWei":"-11061796790489314640961"},"1":{"token":"0x8d0d000ee44948fc98c9b98a4fa4921476f08b0d","symbol":"USD1","decimals":18,"cumulativeYield":"976499547659","status":"mismatch","method":"snapshot-fallback","strictStatus":"mismatch","strictMethod":"canonical-history-mismatch","strictReason":"canonical_history_mismatch","firstDate":"2026-04-15","firstPar":"289441078738080","firstWei":"296690238656689","lastDate":"2026-05-07","lastPar":"289441078738080","lastWei":"297666738204348","days":23,"isLatestSnapshot":true,"hasStaticParWindow":true,"canonicalHistoryCoverageStatus":"fresh","canonicalHistoryLastScannedBlock":25041854,"canonicalHistoryComparisonBlock":25040757,"canonicalHistoryConsistencyStatus":"mismatch","canonicalHistoryTotalDeltaWei":"42987907788211248705","canonicalHistoryAccountCount":3,"canonicalHistoryEventCount":7,"canonicalHistoryHasBorrowAccount":false,"canonicalHistoryHasLegacyUnknownAccount":false,"snapshotYield":"976499547659","netflowYield":"-5598119889853658470552","diff":"-5598119890830158018211","canonicalHistoryNetflowDiffWei":"-5555132279732185426195"},"9":{"token":"","symbol":"UNK","decimals":18,"cumulativeYield":"0","status":"no_snapshot","method":"insufficient-history","strictStatus":"coverage_incomplete","strictMethod":"insufficient-history","strictReason":"snapshot_missing_market","firstDate":"","firstPar":"0","firstWei":"0","lastDate":"","lastPar":"0","lastWei":"0","days":0,"isLatestSnapshot":false,"hasStaticParWindow":false,"canonicalHistoryCoverageStatus":"fresh","canonicalHistoryLastScannedBlock":25041854,"canonicalHistoryComparisonBlock":25040757,"canonicalHistoryConsistencyStatus":"mismatch","canonicalHistoryTotalDeltaWei":"0","canonicalHistoryAccountCount":4,"canonicalHistoryEventCount":9,"canonicalHistoryHasBorrowAccount":false,"canonicalHistoryHasLegacyUnknownAccount":false,"canonicalHistoryNetflowDiffWei":"-32769387949907135999999"}}}