{"version":2,"chain":"ethereum","address":"0x8f9f404b459d56859a9d2239ee85802e1c556661","snapshotDate":"2026-05-05","generatedAt":"2026-05-05T04:02:04.530682Z","summary":{"verified":0,"pre_snapshot_carry":0,"mismatch":1,"no_netflow":0,"no_snapshot":0,"unavailable":0},"strictSummary":{"verified":0,"inferred":0,"mismatch":1,"coverage_incomplete":0,"unavailable":0},"canonicalHistory":{"coverageStatus":"fresh","lastScannedBlock":25025455,"comparisonBlock":25023915,"freshForNetflowComparison":true},"markets":{"1":{"token":"0x8d0d000ee44948fc98c9b98a4fa4921476f08b0d","symbol":"USD1","decimals":18,"cumulativeYield":"452229265994639264186","status":"mismatch","method":"snapshot-fallback","strictStatus":"mismatch","strictMethod":"snapshot-fallback","strictReason":"snapshot_netflow_mismatch","firstDate":"2026-04-17","firstPar":"155843302673071909059534","firstWei":"159779615296302703908850","lastDate":"2026-05-05","lastPar":"148857827335742817802794","lastWei":"153057099697807105731777","days":19,"isLatestSnapshot":true,"hasStaticParWindow":false,"canonicalHistoryCoverageStatus":"fresh","canonicalHistoryLastScannedBlock":25025455,"canonicalHistoryComparisonBlock":25023915,"canonicalHistoryConsistencyStatus":"match","canonicalHistoryTotalDeltaWei":"152592020266350000000000","canonicalHistoryAccountCount":1,"canonicalHistoryEventCount":12,"canonicalHistoryHasBorrowAccount":false,"canonicalHistoryHasLegacyUnknownAccount":false,"snapshotYield":"452229265994639264186","netflowYield":"465079431457105731777","diff":"12850165462466467591","canonicalHistoryNetflowDiffWei":"0"}}}