{"version":2,"chain":"ethereum","address":"0xa4546415f9242707a4e8834a529259301922a16e","snapshotDate":"2026-05-01","generatedAt":"2026-05-01T12:38:59.437104Z","summary":{"verified":0,"pre_snapshot_carry":1,"mismatch":0,"no_netflow":0,"no_snapshot":0,"unavailable":0},"strictSummary":{"verified":0,"inferred":0,"mismatch":1,"coverage_incomplete":0,"unavailable":0},"canonicalHistory":{"coverageStatus":"fresh","lastScannedBlock":24999864,"comparisonBlock":24998496,"freshForNetflowComparison":true},"markets":{"0":{"token":"0xc02aaa39b223fe8d0a0e5c4f27ead9083c756cc2","symbol":"WETH","decimals":18,"cumulativeYield":"601464205648","status":"pre_snapshot_carry","method":"netflow+pre-snapshot-carry","strictStatus":"mismatch","strictMethod":"canonical-history-mismatch","strictReason":"canonical_history_mismatch","firstDate":"2026-01-20","firstPar":"99669250982348","firstWei":"100113848485999","lastDate":"2026-05-01","lastPar":"99669250982348","lastWei":"100270715187996","days":102,"isLatestSnapshot":true,"hasStaticParWindow":true,"canonicalHistoryCoverageStatus":"fresh","canonicalHistoryLastScannedBlock":24999864,"canonicalHistoryComparisonBlock":24998496,"canonicalHistoryConsistencyStatus":"mismatch","canonicalHistoryTotalDeltaWei":"100000000000000","canonicalHistoryAccountCount":1,"canonicalHistoryEventCount":1,"canonicalHistoryHasBorrowAccount":false,"canonicalHistoryHasLegacyUnknownAccount":false,"snapshotYield":"156866701997","netflowYield":"601464205648","diff":"444597503651","canonicalHistoryNetflowDiffWei":"330749017652","verificationBaseline":"all-time-netflow","preSnapshotCarryYield":"444597503651","preSnapshotCarryResidual":"0","preSnapshotCarryWindowType":"exact_post_snapshot_window"}}}