{"version":2,"chain":"ethereum","address":"0xa43c15b7a4c0638f73066b91494262256a445907","snapshotDate":"2026-05-02","generatedAt":"2026-05-02T08:09:09.436362Z","summary":{"verified":0,"pre_snapshot_carry":1,"mismatch":0,"no_netflow":0,"no_snapshot":0,"unavailable":0},"strictSummary":{"verified":0,"inferred":0,"mismatch":1,"coverage_incomplete":0,"unavailable":0},"canonicalHistory":{"coverageStatus":"fresh","lastScannedBlock":25005714,"comparisonBlock":25004761,"freshForNetflowComparison":true},"markets":{"2":{"token":"0xa0b86991c6218b36c1d19d4a2e9eb0ce3606eb48","symbol":"USDC","decimals":6,"cumulativeYield":"18230891","status":"pre_snapshot_carry","method":"netflow+pre-snapshot-carry","strictStatus":"mismatch","strictMethod":"canonical-history-mismatch","strictReason":"canonical_history_mismatch","firstDate":"2026-01-20","firstPar":"497734120","firstWei":"509373209","lastDate":"2026-05-02","lastPar":"497734120","lastWei":"515965011","days":103,"isLatestSnapshot":true,"hasStaticParWindow":true,"canonicalHistoryCoverageStatus":"fresh","canonicalHistoryLastScannedBlock":25005714,"canonicalHistoryComparisonBlock":25004761,"canonicalHistoryConsistencyStatus":"mismatch","canonicalHistoryTotalDeltaWei":"500000000","canonicalHistoryAccountCount":1,"canonicalHistoryEventCount":1,"canonicalHistoryHasBorrowAccount":false,"canonicalHistoryHasLegacyUnknownAccount":false,"snapshotYield":"6591802","netflowYield":"18230891","diff":"11639089","canonicalHistoryNetflowDiffWei":"2265880","verificationBaseline":"all-time-netflow","preSnapshotCarryYield":"11639089","preSnapshotCarryResidual":"0","preSnapshotCarryWindowType":"exact_post_snapshot_window"}}}