{"version":2,"chain":"ethereum","address":"0xca99d35880ce5f6c62ebdc82bdaa02a8ea96101f","snapshotDate":"2026-05-02","generatedAt":"2026-05-02T19:37:36.840357Z","summary":{"verified":0,"pre_snapshot_carry":1,"mismatch":0,"no_netflow":0,"no_snapshot":0,"unavailable":0},"strictSummary":{"verified":0,"inferred":0,"mismatch":1,"coverage_incomplete":0,"unavailable":0},"canonicalHistory":{"coverageStatus":"fresh","lastScannedBlock":25009107,"comparisonBlock":25007746,"freshForNetflowComparison":true},"markets":{"0":{"token":"0xc02aaa39b223fe8d0a0e5c4f27ead9083c756cc2","symbol":"WETH","decimals":18,"cumulativeYield":"605417096","status":"pre_snapshot_carry","method":"netflow+pre-snapshot-carry","strictStatus":"mismatch","strictMethod":"canonical-history-mismatch","strictReason":"canonical_history_mismatch","firstDate":"2026-01-19","firstPar":"99562702055","firstWei":"100006261370","lastDate":"2026-05-02","lastPar":"99562702055","lastWei":"100168119151","days":104,"isLatestSnapshot":true,"hasStaticParWindow":true,"canonicalHistoryCoverageStatus":"fresh","canonicalHistoryLastScannedBlock":25009107,"canonicalHistoryComparisonBlock":25007746,"canonicalHistoryConsistencyStatus":"mismatch","canonicalHistoryTotalDeltaWei":"100000000000","canonicalHistoryAccountCount":1,"canonicalHistoryEventCount":1,"canonicalHistoryHasBorrowAccount":false,"canonicalHistoryHasLegacyUnknownAccount":false,"snapshotYield":"161857781","netflowYield":"605417096","diff":"443559315","canonicalHistoryNetflowDiffWei":"437297945","verificationBaseline":"all-time-netflow","preSnapshotCarryYield":"443559315","preSnapshotCarryResidual":"0","preSnapshotCarryWindowType":"exact_post_snapshot_window"}}}