{"version":2,"chain":"ethereum","address":"0xd75ea59bede05164a140caa4b29804914ebb9aa3","snapshotDate":"2026-05-03","generatedAt":"2026-05-03T13:59:50.996783Z","summary":{"verified":0,"pre_snapshot_carry":0,"mismatch":1,"no_netflow":0,"no_snapshot":0,"unavailable":0},"strictSummary":{"verified":0,"inferred":0,"mismatch":1,"coverage_incomplete":0,"unavailable":0},"canonicalHistory":{"coverageStatus":"fresh","lastScannedBlock":25014495,"comparisonBlock":25013261,"freshForNetflowComparison":true},"markets":{"1":{"token":"0x8d0d000ee44948fc98c9b98a4fa4921476f08b0d","symbol":"USD1","decimals":18,"cumulativeYield":"430749607629557009355","status":"mismatch","method":"snapshot-fallback","strictStatus":"mismatch","strictMethod":"canonical-history-mismatch","strictReason":"canonical_history_mismatch","firstDate":"2026-01-19","firstPar":"32113225050886801085","firstWei":"32691902130663141650","lastDate":"2026-05-03","lastPar":"47489598864557744446079","lastWei":"48822268188460416674695","days":105,"isLatestSnapshot":true,"hasStaticParWindow":false,"canonicalHistoryCoverageStatus":"fresh","canonicalHistoryLastScannedBlock":25014495,"canonicalHistoryComparisonBlock":25013261,"canonicalHistoryConsistencyStatus":"mismatch","canonicalHistoryTotalDeltaWei":"48386733180531835278706","canonicalHistoryAccountCount":1,"canonicalHistoryEventCount":140,"canonicalHistoryHasBorrowAccount":false,"canonicalHistoryHasLegacyUnknownAccount":false,"snapshotYield":"430749607629557009355","netflowYield":"-1749936135260850322365769","diff":"-1750366884868479879375124","canonicalHistoryNetflowDiffWei":"-1750371670268778903761758"}}}