{"version":2,"chain":"ethereum","address":"0xe6b3062115dffb4e1a35bf059636cfe7e2c6866e","snapshotDate":"2026-05-04","generatedAt":"2026-05-04T04:19:15.780903Z","summary":{"verified":0,"pre_snapshot_carry":1,"mismatch":1,"no_netflow":0,"no_snapshot":0,"unavailable":0},"strictSummary":{"verified":0,"inferred":0,"mismatch":2,"coverage_incomplete":0,"unavailable":0},"canonicalHistory":{"coverageStatus":"fresh","lastScannedBlock":25018310,"comparisonBlock":25016636,"freshForNetflowComparison":true},"markets":{"1":{"token":"0x8d0d000ee44948fc98c9b98a4fa4921476f08b0d","symbol":"USD1","decimals":18,"cumulativeYield":"502469253324141238446","status":"mismatch","method":"snapshot-fallback","strictStatus":"mismatch","strictMethod":"canonical-history-mismatch","strictReason":"canonical_history_mismatch","firstDate":"2026-04-15","firstPar":"114215855065773281566759","firstWei":"117076433813690788355737","lastDate":"2026-05-04","lastPar":"310430381282063452107480","lastWei":"319161109860967471582527","days":20,"isLatestSnapshot":true,"hasStaticParWindow":false,"canonicalHistoryCoverageStatus":"fresh","canonicalHistoryLastScannedBlock":25018310,"canonicalHistoryComparisonBlock":25016636,"canonicalHistoryConsistencyStatus":"mismatch","canonicalHistoryTotalDeltaWei":"318074119475351767611148","canonicalHistoryAccountCount":1,"canonicalHistoryEventCount":6,"canonicalHistoryHasBorrowAccount":false,"canonicalHistoryHasLegacyUnknownAccount":false,"snapshotYield":"502469253324141238446","netflowYield":"-61901100483390184944149","diff":"-62403569736714326182595","canonicalHistoryNetflowDiffWei":"-62988090869005888915528"},"2":{"token":"0xa0b86991c6218b36c1d19d4a2e9eb0ce3606eb48","symbol":"USDC","decimals":6,"cumulativeYield":"48278748257","status":"pre_snapshot_carry","method":"netflow+pre-snapshot-carry","strictStatus":"mismatch","strictMethod":"canonical-history-mismatch","strictReason":"canonical_history_mismatch","firstDate":"2026-04-27","firstPar":"452912460984","firstWei":"469273790477","lastDate":"2026-05-04","lastPar":"452912460984","lastWei":"469596436346","days":8,"isLatestSnapshot":true,"hasStaticParWindow":true,"canonicalHistoryCoverageStatus":"fresh","canonicalHistoryLastScannedBlock":25018310,"canonicalHistoryComparisonBlock":25016636,"canonicalHistoryConsistencyStatus":"mismatch","canonicalHistoryTotalDeltaWei":"469283239427","canonicalHistoryAccountCount":1,"canonicalHistoryEventCount":7,"canonicalHistoryHasBorrowAccount":false,"canonicalHistoryHasLegacyUnknownAccount":false,"snapshotYield":"322645869","netflowYield":"48278748257","diff":"47956102388","canonicalHistoryNetflowDiffWei":"47965551338","verificationBaseline":"all-time-netflow","preSnapshotCarryYield":"47956102388","preSnapshotCarryResidual":"0","preSnapshotCarryWindowType":"exact_post_snapshot_window"}}}