{"version":2,"chain":"arbitrum","address":"0x28d424ca841f4f1d08d76d491f3a221783c85581","snapshotDate":"2026-05-06","generatedAt":"2026-05-06T21:35:04.771113Z","summary":{"verified":0,"pre_snapshot_carry":3,"mismatch":3,"no_netflow":2,"no_snapshot":2,"unavailable":0},"strictSummary":{"verified":0,"inferred":1,"mismatch":5,"coverage_incomplete":4,"unavailable":0},"canonicalHistory":{"coverageStatus":"fresh","lastScannedBlock":460112208,"comparisonBlock":460093008,"freshForNetflowComparison":true},"markets":{"0":{"token":"0x82af49447d8a07e3bd95bd0d56f35241523fbab1","symbol":"WETH","decimals":18,"cumulativeYield":"158532255837","status":"mismatch","method":"snapshot-fallback","strictStatus":"mismatch","strictMethod":"canonical-history-mismatch","strictReason":"canonical_history_mismatch","firstDate":"2026-01-21","firstPar":"12140400","firstWei":"13292682","lastDate":"2026-05-06","lastPar":"108727986754725","lastWei":"119591052718854","days":106,"isLatestSnapshot":true,"hasStaticParWindow":false,"canonicalHistoryCoverageStatus":"fresh","canonicalHistoryLastScannedBlock":460112208,"canonicalHistoryComparisonBlock":460093008,"canonicalHistoryConsistencyStatus":"mismatch","canonicalHistoryTotalDeltaWei":"110222740338874","canonicalHistoryAccountCount":14,"canonicalHistoryEventCount":41,"canonicalHistoryHasBorrowAccount":false,"canonicalHistoryHasLegacyUnknownAccount":false,"snapshotYield":"158532255837","netflowYield":"-48095319536687594","diff":"-48095478068943431","canonicalHistoryNetflowDiffWei":"-48104687849067574"},"2":{"token":"0xff970a61a04b1ca14834a43f5de4533ebddb5cc8","symbol":"USDC.e","decimals":6,"cumulativeYield":"633","status":"mismatch","method":"snapshot-fallback","strictStatus":"mismatch","strictMethod":"canonical-history-mismatch","strictReason":"canonical_history_mismatch","firstDate":"2026-01-21","firstPar":"1","firstWei":"1","lastDate":"2026-05-06","lastPar":"176265","lastWei":"228219","days":106,"isLatestSnapshot":true,"hasStaticParWindow":false,"canonicalHistoryCoverageStatus":"fresh","canonicalHistoryLastScannedBlock":460112208,"canonicalHistoryComparisonBlock":460093008,"canonicalHistoryConsistencyStatus":"mismatch","canonicalHistoryTotalDeltaWei":"1","canonicalHistoryAccountCount":2,"canonicalHistoryEventCount":3,"canonicalHistoryHasBorrowAccount":false,"canonicalHistoryHasLegacyUnknownAccount":false,"snapshotYield":"633","netflowYield":"228219","diff":"227586","canonicalHistoryNetflowDiffWei":"1"},"4":{"token":"0x2f2a2543b76a4166549f7aab2e75bef0aefc5b0f","symbol":"WBTC","decimals":8,"cumulativeYield":"17","status":"pre_snapshot_carry","method":"netflow+pre-snapshot-carry","strictStatus":"inferred","strictMethod":"netflow+pre-snapshot-carry","strictReason":"pre_snapshot_carry_requires_inference","firstDate":"2026-04-15","firstPar":"17","firstWei":"17","lastDate":"2026-05-06","lastPar":"17","lastWei":"17","days":22,"isLatestSnapshot":true,"hasStaticParWindow":true,"canonicalHistoryCoverageStatus":"fresh","canonicalHistoryLastScannedBlock":460112208,"canonicalHistoryComparisonBlock":460093008,"canonicalHistoryConsistencyStatus":"match","canonicalHistoryTotalDeltaWei":"0","canonicalHistoryAccountCount":1,"canonicalHistoryEventCount":1,"canonicalHistoryHasBorrowAccount":false,"canonicalHistoryHasLegacyUnknownAccount":false,"snapshotYield":"0","netflowYield":"17","diff":"17","canonicalHistoryNetflowDiffWei":"0","verificationBaseline":"all-time-netflow","preSnapshotCarryYield":"17","preSnapshotCarryResidual":"0","preSnapshotCarryWindowType":"exact_post_snapshot_window"},"8":{"token":"0x85667409a723684fe1e57dd1abde8d88c2f54214","symbol":"mGLP","decimals":18,"cumulativeYield":"0","status":"mismatch","method":"snapshot-fallback","strictStatus":"mismatch","strictMethod":"canonical-history-mismatch","strictReason":"canonical_history_mismatch","firstDate":"2026-04-15","firstPar":"386672812009059535","firstWei":"386672812009059535","lastDate":"2026-05-06","lastPar":"386672812009059535","lastWei":"386672812009059535","days":22,"isLatestSnapshot":true,"hasStaticParWindow":true,"canonicalHistoryCoverageStatus":"fresh","canonicalHistoryLastScannedBlock":460112208,"canonicalHistoryComparisonBlock":460093008,"canonicalHistoryConsistencyStatus":"mismatch","canonicalHistoryTotalDeltaWei":"386672812009059535","canonicalHistoryAccountCount":4,"canonicalHistoryEventCount":8,"canonicalHistoryHasBorrowAccount":true,"canonicalHistoryHasLegacyUnknownAccount":false,"snapshotYield":"0","netflowYield":"-314422176831302670","diff":"-314422176831302670","canonicalHistoryNetflowDiffWei":"-314422176831302670"},"9":{"token":"0x5c80ac681b6b0e7ef6e0751211012601e6cfb043","symbol":"dplvGLP","decimals":18,"cumulativeYield":"0","status":"no_netflow","method":"snapshot-only","strictStatus":"coverage_incomplete","strictMethod":"snapshot-only","strictReason":"netflow_missing_market","firstDate":"2026-04-15","firstPar":"65167667221913312","firstWei":"65167667221913312","lastDate":"2026-05-06","lastPar":"65167667221913312","lastWei":"65167667221913312","days":22,"isLatestSnapshot":true,"hasStaticParWindow":true,"canonicalHistoryCoverageStatus":"fresh","canonicalHistoryLastScannedBlock":460112208,"canonicalHistoryComparisonBlock":460093008,"canonicalHistoryConsistencyStatus":"none","canonicalHistoryTotalDeltaWei":"0","canonicalHistoryAccountCount":0,"canonicalHistoryEventCount":0,"canonicalHistoryHasBorrowAccount":false,"canonicalHistoryHasLegacyUnknownAccount":false,"snapshotYield":"0"},"13":{"token":"","symbol":"UNK","decimals":18,"cumulativeYield":"0","status":"no_snapshot","method":"insufficient-history","strictStatus":"coverage_incomplete","strictMethod":"insufficient-history","strictReason":"snapshot_missing_market","firstDate":"","firstPar":"0","firstWei":"0","lastDate":"","lastPar":"0","lastWei":"0","days":0,"isLatestSnapshot":false,"hasStaticParWindow":false,"canonicalHistoryCoverageStatus":"fresh","canonicalHistoryLastScannedBlock":460112208,"canonicalHistoryComparisonBlock":460093008,"canonicalHistoryConsistencyStatus":"mismatch","canonicalHistoryTotalDeltaWei":"-128658889997632677","canonicalHistoryAccountCount":2,"canonicalHistoryEventCount":4,"canonicalHistoryHasBorrowAccount":true,"canonicalHistoryHasLegacyUnknownAccount":false,"canonicalHistoryNetflowDiffWei":"-329055102445229083"},"14":{"token":"0x5979d7b546e38e414f7e9822514be443a4800529","symbol":"wstETH","decimals":18,"cumulativeYield":"1302970279829","status":"pre_snapshot_carry","method":"netflow+pre-snapshot-carry","strictStatus":"mismatch","strictMethod":"canonical-history-mismatch","strictReason":"canonical_history_mismatch","firstDate":"2026-04-15","firstPar":"43466470681339","firstWei":"44856177830122","lastDate":"2026-05-06","lastPar":"43466470681339","lastWei":"44857490468663","days":22,"isLatestSnapshot":true,"hasStaticParWindow":true,"canonicalHistoryCoverageStatus":"fresh","canonicalHistoryLastScannedBlock":460112208,"canonicalHistoryComparisonBlock":460093008,"canonicalHistoryConsistencyStatus":"mismatch","canonicalHistoryTotalDeltaWei":"43554520188835","canonicalHistoryAccountCount":3,"canonicalHistoryEventCount":5,"canonicalHistoryHasBorrowAccount":false,"canonicalHistoryHasLegacyUnknownAccount":false,"snapshotYield":"1312638541","netflowYield":"1302970279829","diff":"1301657641288","canonicalHistoryNetflowDiffWei":"1","verificationBaseline":"all-time-netflow","preSnapshotCarryYield":"1301657641288","preSnapshotCarryResidual":"0","preSnapshotCarryWindowType":"exact_post_snapshot_window"},"15":{"token":"0xec70dcb4a1efa46b8f2d97c310c9c4790ba5ffa8","symbol":"rETH","decimals":18,"cumulativeYield":"1625741177382","status":"pre_snapshot_carry","method":"netflow+pre-snapshot-carry","strictStatus":"mismatch","strictMethod":"canonical-history-mismatch","strictReason":"canonical_history_mismatch","firstDate":"2026-04-15","firstPar":"45283540834830","firstWei":"47204019333908","lastDate":"2026-05-06","lastPar":"45283540834830","lastWei":"47204205715671","days":22,"isLatestSnapshot":true,"hasStaticParWindow":true,"canonicalHistoryCoverageStatus":"fresh","canonicalHistoryLastScannedBlock":460112208,"canonicalHistoryComparisonBlock":460093008,"canonicalHistoryConsistencyStatus":"mismatch","canonicalHistoryTotalDeltaWei":"45578464538290","canonicalHistoryAccountCount":3,"canonicalHistoryEventCount":5,"canonicalHistoryHasBorrowAccount":false,"canonicalHistoryHasLegacyUnknownAccount":false,"snapshotYield":"186381763","netflowYield":"1625741177382","diff":"1625554795619","canonicalHistoryNetflowDiffWei":"1","verificationBaseline":"all-time-netflow","preSnapshotCarryYield":"1625554795619","preSnapshotCarryResidual":"0","preSnapshotCarryWindowType":"exact_post_snapshot_window"},"17":{"token":"","symbol":"UNK","decimals":18,"cumulativeYield":"0","status":"no_snapshot","method":"insufficient-history","strictStatus":"coverage_incomplete","strictMethod":"insufficient-history","strictReason":"snapshot_missing_market","firstDate":"","firstPar":"0","firstWei":"0","lastDate":"","lastPar":"0","lastWei":"0","days":0,"isLatestSnapshot":false,"hasStaticParWindow":false,"canonicalHistoryCoverageStatus":"fresh","canonicalHistoryLastScannedBlock":460112208,"canonicalHistoryComparisonBlock":460093008,"canonicalHistoryConsistencyStatus":"mismatch","canonicalHistoryTotalDeltaWei":"-1717052","canonicalHistoryAccountCount":7,"canonicalHistoryEventCount":23,"canonicalHistoryHasBorrowAccount":false,"canonicalHistoryHasLegacyUnknownAccount":false,"canonicalHistoryNetflowDiffWei":"-13235970"},"30":{"token":"0x790ff506ac24b03a21f3d0019227447ae2b55ca5","symbol":"dGMX","decimals":18,"cumulativeYield":"0","status":"no_netflow","method":"snapshot-only","strictStatus":"coverage_incomplete","strictMethod":"snapshot-only","strictReason":"netflow_missing_market","firstDate":"2026-04-15","firstPar":"5621697806741803","firstWei":"5621697806741803","lastDate":"2026-05-06","lastPar":"5621697806741803","lastWei":"5621697806741803","days":22,"isLatestSnapshot":true,"hasStaticParWindow":true,"canonicalHistoryCoverageStatus":"fresh","canonicalHistoryLastScannedBlock":460112208,"canonicalHistoryComparisonBlock":460093008,"canonicalHistoryConsistencyStatus":"none","canonicalHistoryTotalDeltaWei":"0","canonicalHistoryAccountCount":0,"canonicalHistoryEventCount":0,"canonicalHistoryHasBorrowAccount":false,"canonicalHistoryHasLegacyUnknownAccount":false,"snapshotYield":"0"}}}