{"version":2,"chain":"arbitrum","address":"0x63712c2f30f48ff20beb3837578071b70cea9f07","snapshotDate":"2026-05-06","generatedAt":"2026-05-07T04:08:33.903353Z","summary":{"verified":0,"pre_snapshot_carry":1,"mismatch":7,"no_netflow":0,"no_snapshot":6,"unavailable":0},"strictSummary":{"verified":0,"inferred":0,"mismatch":8,"coverage_incomplete":6,"unavailable":0},"canonicalHistory":{"coverageStatus":"fresh","lastScannedBlock":460206107,"comparisonBlock":460093008,"freshForNetflowComparison":true},"markets":{"0":{"token":"0x82af49447d8a07e3bd95bd0d56f35241523fbab1","symbol":"WETH","decimals":18,"cumulativeYield":"36149572","status":"mismatch","method":"snapshot-fallback","strictStatus":"mismatch","strictMethod":"canonical-history-mismatch","strictReason":"canonical_history_mismatch","firstDate":"2026-01-21","firstPar":"7233610680","firstWei":"7920174664","lastDate":"2026-05-06","lastPar":"7233610680","lastWei":"7956324236","days":106,"isLatestSnapshot":true,"hasStaticParWindow":true,"canonicalHistoryCoverageStatus":"fresh","canonicalHistoryLastScannedBlock":460206107,"canonicalHistoryComparisonBlock":460093008,"canonicalHistoryConsistencyStatus":"mismatch","canonicalHistoryTotalDeltaWei":"-406643014743599761","canonicalHistoryAccountCount":2,"canonicalHistoryEventCount":32,"canonicalHistoryHasBorrowAccount":true,"canonicalHistoryHasLegacyUnknownAccount":false,"snapshotYield":"36149572","netflowYield":"-7710724814426136756391","diff":"-7710724814426172905963","canonicalHistoryNetflowDiffWei":"-7711131457448836680388"},"1":{"token":"","symbol":"UNK","decimals":18,"cumulativeYield":"0","status":"no_snapshot","method":"insufficient-history","strictStatus":"coverage_incomplete","strictMethod":"insufficient-history","strictReason":"snapshot_missing_market","firstDate":"","firstPar":"0","firstWei":"0","lastDate":"","lastPar":"0","lastWei":"0","days":0,"isLatestSnapshot":false,"hasStaticParWindow":false,"canonicalHistoryCoverageStatus":"fresh","canonicalHistoryLastScannedBlock":460206107,"canonicalHistoryComparisonBlock":460093008,"canonicalHistoryConsistencyStatus":"mismatch","canonicalHistoryTotalDeltaWei":"2750047965034788568","canonicalHistoryAccountCount":7,"canonicalHistoryEventCount":18,"canonicalHistoryHasBorrowAccount":true,"canonicalHistoryHasLegacyUnknownAccount":false,"canonicalHistoryNetflowDiffWei":"-148884003912840475"},"2":{"token":"","symbol":"UNK","decimals":18,"cumulativeYield":"0","status":"no_snapshot","method":"insufficient-history","strictStatus":"coverage_incomplete","strictMethod":"insufficient-history","strictReason":"snapshot_missing_market","firstDate":"","firstPar":"0","firstWei":"0","lastDate":"","lastPar":"0","lastWei":"0","days":0,"isLatestSnapshot":false,"hasStaticParWindow":false,"canonicalHistoryCoverageStatus":"fresh","canonicalHistoryLastScannedBlock":460206107,"canonicalHistoryComparisonBlock":460093008,"canonicalHistoryConsistencyStatus":"mismatch","canonicalHistoryTotalDeltaWei":"-1241554","canonicalHistoryAccountCount":9,"canonicalHistoryEventCount":24,"canonicalHistoryHasBorrowAccount":true,"canonicalHistoryHasLegacyUnknownAccount":false,"canonicalHistoryNetflowDiffWei":"-5189034512"},"3":{"token":"0xf97f4df75117a78c1a5a0dbb814af92458539fb4","symbol":"LINK","decimals":18,"cumulativeYield":"53905670781680720","status":"mismatch","method":"snapshot-fallback","strictStatus":"mismatch","strictMethod":"canonical-history-mismatch","strictReason":"canonical_history_mismatch","firstDate":"2026-04-15","firstPar":"109643570696623806654","firstWei":"120824599569780403774","lastDate":"2026-05-06","lastPar":"109643570696623806654","lastWei":"120878505240562084494","days":22,"isLatestSnapshot":true,"hasStaticParWindow":true,"canonicalHistoryCoverageStatus":"fresh","canonicalHistoryLastScannedBlock":460206107,"canonicalHistoryComparisonBlock":460093008,"canonicalHistoryConsistencyStatus":"mismatch","canonicalHistoryTotalDeltaWei":"117433152126740219106","canonicalHistoryAccountCount":1,"canonicalHistoryEventCount":3,"canonicalHistoryHasBorrowAccount":true,"canonicalHistoryHasLegacyUnknownAccount":false,"snapshotYield":"53905670781680720","netflowYield":"-3764013619907675059","diff":"-3817919290689355779","canonicalHistoryNetflowDiffWei":"-7209366733729540447"},"4":{"token":"0x2f2a2543b76a4166549f7aab2e75bef0aefc5b0f","symbol":"WBTC","decimals":8,"cumulativeYield":"5668393","status":"pre_snapshot_carry","method":"netflow+pre-snapshot-carry","strictStatus":"mismatch","strictMethod":"canonical-history-mismatch","strictReason":"canonical_history_mismatch","firstDate":"2026-04-15","firstPar":"51529","firstWei":"54614","lastDate":"2026-05-06","lastPar":"51529","lastWei":"54630","days":22,"isLatestSnapshot":true,"hasStaticParWindow":true,"canonicalHistoryCoverageStatus":"fresh","canonicalHistoryLastScannedBlock":460206107,"canonicalHistoryComparisonBlock":460093008,"canonicalHistoryConsistencyStatus":"mismatch","canonicalHistoryTotalDeltaWei":"70673","canonicalHistoryAccountCount":1,"canonicalHistoryEventCount":7,"canonicalHistoryHasBorrowAccount":true,"canonicalHistoryHasLegacyUnknownAccount":false,"snapshotYield":"16","netflowYield":"5668393","diff":"5668377","canonicalHistoryNetflowDiffWei":"5684436","verificationBaseline":"all-time-netflow","preSnapshotCarryYield":"5668377","preSnapshotCarryResidual":"0","preSnapshotCarryWindowType":"exact_post_snapshot_window"},"5":{"token":"0xfd086bc7cd5c481dcc9c85ebe478a1c0b69fcbb9","symbol":"USDT","decimals":6,"cumulativeYield":"0","status":"mismatch","method":"snapshot-fallback","strictStatus":"mismatch","strictMethod":"canonical-history-mismatch","strictReason":"canonical_history_mismatch","firstDate":"2026-01-21","firstPar":"9","firstWei":"12","lastDate":"2026-05-06","lastPar":"25","lastWei":"33","days":106,"isLatestSnapshot":true,"hasStaticParWindow":false,"canonicalHistoryCoverageStatus":"fresh","canonicalHistoryLastScannedBlock":460206107,"canonicalHistoryComparisonBlock":460093008,"canonicalHistoryConsistencyStatus":"mismatch","canonicalHistoryTotalDeltaWei":"-29177641","canonicalHistoryAccountCount":9,"canonicalHistoryEventCount":51,"canonicalHistoryHasBorrowAccount":true,"canonicalHistoryHasLegacyUnknownAccount":false,"snapshotYield":"0","netflowYield":"-9360971471","diff":"-9360971471","canonicalHistoryNetflowDiffWei":"-9390149145"},"7":{"token":"0x912ce59144191c1204e64559fe8253a0e49e6548","symbol":"ARB","decimals":18,"cumulativeYield":"3651228372454020281","status":"mismatch","method":"snapshot-fallback","strictStatus":"mismatch","strictMethod":"canonical-history-mismatch","strictReason":"canonical_history_mismatch","firstDate":"2026-01-21","firstPar":"33043517404","firstWei":"33977222086","lastDate":"2026-05-06","lastPar":"684260246544731424214","lastWei":"715868016857298563349","days":106,"isLatestSnapshot":true,"hasStaticParWindow":false,"canonicalHistoryCoverageStatus":"fresh","canonicalHistoryLastScannedBlock":460206107,"canonicalHistoryComparisonBlock":460093008,"canonicalHistoryConsistencyStatus":"mismatch","canonicalHistoryTotalDeltaWei":"689697132261449983679","canonicalHistoryAccountCount":2,"canonicalHistoryEventCount":16,"canonicalHistoryHasBorrowAccount":true,"canonicalHistoryHasLegacyUnknownAccount":false,"snapshotYield":"3651228372454020281","netflowYield":"-662825573733408515284","diff":"-666476802105862535565","canonicalHistoryNetflowDiffWei":"-688996458329257094954"},"12":{"token":"0xfa7f8980b0f1e64a2062791cc3b0871572f1f7f0","symbol":"UNI","decimals":18,"cumulativeYield":"4995763045199935","status":"mismatch","method":"snapshot-fallback","strictStatus":"mismatch","strictMethod":"canonical-history-mismatch","strictReason":"canonical_history_mismatch","firstDate":"2026-01-21","firstPar":"787549009","firstWei":"794507347","lastDate":"2026-05-06","lastPar":"240501221894575006551","lastWei":"242651147523664679841","days":106,"isLatestSnapshot":true,"hasStaticParWindow":false,"canonicalHistoryCoverageStatus":"fresh","canonicalHistoryLastScannedBlock":460206107,"canonicalHistoryComparisonBlock":460093008,"canonicalHistoryConsistencyStatus":"mismatch","canonicalHistoryTotalDeltaWei":"242219636613900000000","canonicalHistoryAccountCount":2,"canonicalHistoryEventCount":3,"canonicalHistoryHasBorrowAccount":true,"canonicalHistoryHasLegacyUnknownAccount":false,"snapshotYield":"4995763045199935","netflowYield":"-240069710984898457181","diff":"-240074706747943657116","canonicalHistoryNetflowDiffWei":"-240501221894663137022"},"17":{"token":"","symbol":"UNK","decimals":18,"cumulativeYield":"0","status":"no_snapshot","method":"insufficient-history","strictStatus":"coverage_incomplete","strictMethod":"insufficient-history","strictReason":"snapshot_missing_market","firstDate":"","firstPar":"0","firstWei":"0","lastDate":"","lastPar":"0","lastWei":"0","days":0,"isLatestSnapshot":false,"hasStaticParWindow":false,"canonicalHistoryCoverageStatus":"fresh","canonicalHistoryLastScannedBlock":460206107,"canonicalHistoryComparisonBlock":460093008,"canonicalHistoryConsistencyStatus":"mismatch","canonicalHistoryTotalDeltaWei":"-39905375","canonicalHistoryAccountCount":17,"canonicalHistoryEventCount":52,"canonicalHistoryHasBorrowAccount":true,"canonicalHistoryHasLegacyUnknownAccount":false,"canonicalHistoryNetflowDiffWei":"-13234007095"},"18":{"token":"0x3d9907f9a368ad0a51be60f7da3b97cf940982d8","symbol":"GRAIL","decimals":18,"cumulativeYield":"75317","status":"mismatch","method":"snapshot-fallback","strictStatus":"mismatch","strictMethod":"canonical-history-mismatch","strictReason":"canonical_history_mismatch","firstDate":"2026-01-21","firstPar":"1327566","firstWei":"1347048","lastDate":"2026-05-06","lastPar":"1327566","lastWei":"1422365","days":106,"isLatestSnapshot":true,"hasStaticParWindow":true,"canonicalHistoryCoverageStatus":"fresh","canonicalHistoryLastScannedBlock":460206107,"canonicalHistoryComparisonBlock":460093008,"canonicalHistoryConsistencyStatus":"mismatch","canonicalHistoryTotalDeltaWei":"894859999933644","canonicalHistoryAccountCount":8,"canonicalHistoryEventCount":29,"canonicalHistoryHasBorrowAccount":true,"canonicalHistoryHasLegacyUnknownAccount":false,"snapshotYield":"75317","netflowYield":"-336889012068200829","diff":"-336889012068276146","canonicalHistoryNetflowDiffWei":"-335994152069689550"},"21":{"token":"0x0c880f6761f1af8d9aa9c466984b80dab9a8c9e8","symbol":"PENDLE","decimals":18,"cumulativeYield":"2314851595822433","status":"mismatch","method":"snapshot-fallback","strictStatus":"mismatch","strictMethod":"canonical-history-mismatch","strictReason":"canonical_history_mismatch","firstDate":"2026-01-21","firstPar":"356722873688","firstWei":"360384734606","lastDate":"2026-05-06","lastPar":"105602542987249100271","lastWei":"106704416658069399217","days":106,"isLatestSnapshot":true,"hasStaticParWindow":false,"canonicalHistoryCoverageStatus":"fresh","canonicalHistoryLastScannedBlock":460206107,"canonicalHistoryComparisonBlock":460093008,"canonicalHistoryConsistencyStatus":"mismatch","canonicalHistoryTotalDeltaWei":"109316934857934834996","canonicalHistoryAccountCount":5,"canonicalHistoryEventCount":44,"canonicalHistoryHasBorrowAccount":true,"canonicalHistoryHasLegacyUnknownAccount":false,"snapshotYield":"2314851595822433","netflowYield":"-8423641142068150885","diff":"-8425955993663973318","canonicalHistoryNetflowDiffWei":"-5811122942202715106"},"29":{"token":"","symbol":"UNK","decimals":18,"cumulativeYield":"0","status":"no_snapshot","method":"insufficient-history","strictStatus":"coverage_incomplete","strictMethod":"insufficient-history","strictReason":"snapshot_missing_market","firstDate":"","firstPar":"0","firstWei":"0","lastDate":"","lastPar":"0","lastWei":"0","days":0,"isLatestSnapshot":false,"hasStaticParWindow":false,"canonicalHistoryCoverageStatus":"fresh","canonicalHistoryLastScannedBlock":460206107,"canonicalHistoryComparisonBlock":460093008,"canonicalHistoryConsistencyStatus":"mismatch","canonicalHistoryTotalDeltaWei":"620157564036266752","canonicalHistoryAccountCount":9,"canonicalHistoryEventCount":73,"canonicalHistoryHasBorrowAccount":true,"canonicalHistoryHasLegacyUnknownAccount":false,"canonicalHistoryNetflowDiffWei":"-43966638181294644235"},"46":{"token":"","symbol":"UNK","decimals":18,"cumulativeYield":"0","status":"no_snapshot","method":"insufficient-history","strictStatus":"coverage_incomplete","strictMethod":"insufficient-history","strictReason":"snapshot_missing_market","firstDate":"","firstPar":"0","firstWei":"0","lastDate":"","lastPar":"0","lastWei":"0","days":0,"isLatestSnapshot":false,"hasStaticParWindow":false,"canonicalHistoryCoverageStatus":"fresh","canonicalHistoryLastScannedBlock":460206107,"canonicalHistoryComparisonBlock":460093008,"canonicalHistoryConsistencyStatus":"mismatch","canonicalHistoryTotalDeltaWei":"1856688710589775977","canonicalHistoryAccountCount":5,"canonicalHistoryEventCount":14,"canonicalHistoryHasBorrowAccount":true,"canonicalHistoryHasLegacyUnknownAccount":false,"canonicalHistoryNetflowDiffWei":"1435047272823212"},"48":{"token":"","symbol":"UNK","decimals":18,"cumulativeYield":"0","status":"no_snapshot","method":"insufficient-history","strictStatus":"coverage_incomplete","strictMethod":"insufficient-history","strictReason":"snapshot_missing_market","firstDate":"","firstPar":"0","firstWei":"0","lastDate":"","lastPar":"0","lastWei":"0","days":0,"isLatestSnapshot":false,"hasStaticParWindow":false,"canonicalHistoryCoverageStatus":"fresh","canonicalHistoryLastScannedBlock":460206107,"canonicalHistoryComparisonBlock":460093008,"canonicalHistoryConsistencyStatus":"mismatch","canonicalHistoryTotalDeltaWei":"-7415452272293088832","canonicalHistoryAccountCount":12,"canonicalHistoryEventCount":34,"canonicalHistoryHasBorrowAccount":true,"canonicalHistoryHasLegacyUnknownAccount":false,"canonicalHistoryNetflowDiffWei":"-6446731051007564656884"}}}