{"version":2,"chain":"mantle","address":"0xbe3c90d34b757587c62852dcd57f7c8e1bc5547c","snapshotDate":"2026-05-02","generatedAt":"2026-05-02T15:26:38.482073Z","summary":{"verified":0,"pre_snapshot_carry":3,"mismatch":0,"no_netflow":2,"no_snapshot":0,"unavailable":0},"strictSummary":{"verified":0,"inferred":3,"mismatch":0,"coverage_incomplete":2,"unavailable":0},"canonicalHistory":{"coverageStatus":"fresh","lastScannedBlock":94802620,"comparisonBlock":94800081,"freshForNetflowComparison":true},"markets":{"1":{"token":"0x78c1b0c915c4faa5fffa6cabf0219da63d7f4cb8","symbol":"WMNT","decimals":18,"cumulativeYield":"26542718918730234","status":"pre_snapshot_carry","method":"netflow+pre-snapshot-carry","strictStatus":"inferred","strictMethod":"netflow+pre-snapshot-carry","strictReason":"pre_snapshot_carry_requires_inference","firstDate":"2026-04-15","firstPar":"966847506638038284","firstWei":"1026542141105959683","lastDate":"2026-05-02","lastPar":"966847506638038284","lastWei":"1026542718918730234","days":18,"isLatestSnapshot":true,"hasStaticParWindow":true,"canonicalHistoryCoverageStatus":"fresh","canonicalHistoryLastScannedBlock":94802620,"canonicalHistoryComparisonBlock":94800081,"canonicalHistoryConsistencyStatus":"match","canonicalHistoryTotalDeltaWei":"1000000000000000000","canonicalHistoryAccountCount":3,"canonicalHistoryEventCount":9,"canonicalHistoryHasBorrowAccount":false,"canonicalHistoryHasLegacyUnknownAccount":false,"snapshotYield":"577812770551","netflowYield":"26542718918730234","diff":"26542141105959683","endingPar":"966847506638038284","canonicalHistoryNetflowDiffWei":"0","verificationBaseline":"all-time-netflow","preSnapshotCarryYield":"26542141105959683","preSnapshotCarryResidual":"0","preSnapshotCarryWindowType":"exact_post_snapshot_window"},"5":{"token":"0xcda86a272531e8640cd7f1a92c01839911b90bb0","symbol":"mETH","decimals":18,"cumulativeYield":"660161860448","status":"pre_snapshot_carry","method":"recent-cycle+pre-snapshot-carry","strictStatus":"inferred","strictMethod":"recent-cycle+pre-snapshot-carry","strictReason":"pre_snapshot_carry_requires_inference","firstDate":"2026-04-15","firstPar":"99957399313366","firstWei":"100795544491458","lastDate":"2026-05-02","lastPar":"99957399313366","lastWei":"100795584021823","days":18,"isLatestSnapshot":true,"hasStaticParWindow":true,"canonicalHistoryCoverageStatus":"fresh","canonicalHistoryLastScannedBlock":94802620,"canonicalHistoryComparisonBlock":94800081,"canonicalHistoryConsistencyStatus":"match","canonicalHistoryTotalDeltaWei":"100135421822980","canonicalHistoryAccountCount":3,"canonicalHistoryEventCount":8,"canonicalHistoryHasBorrowAccount":false,"canonicalHistoryHasLegacyUnknownAccount":false,"snapshotYield":"39530365","netflowYield":"660162198843","diff":"660122668478","recentCycleYield":"660161860448","recentCycleDiff":"660122330083","recentCycleNetFlow":"100135422161375","resetPar":"206428","endingPar":"99957399313366","canonicalHistoryNetflowDiffWei":"0","verificationBaseline":"recent-cycle","preSnapshotCarryYield":"660122330083","preSnapshotCarryResidual":"0","preSnapshotCarryWindowType":"exact_post_snapshot_window"},"8":{"token":"0x5be26527e817998a7206475496fde1e68957c5a6","symbol":"USDY","decimals":18,"cumulativeYield":"9996271256448681","status":"pre_snapshot_carry","method":"recent-cycle+pre-snapshot-carry","strictStatus":"inferred","strictMethod":"recent-cycle+pre-snapshot-carry","strictReason":"pre_snapshot_carry_requires_inference","firstDate":"2026-04-15","firstPar":"110305575813442922","firstWei":"121065144063348971","lastDate":"2026-05-02","lastPar":"110305575813442922","lastWei":"121095424411933608","days":18,"isLatestSnapshot":true,"hasStaticParWindow":true,"canonicalHistoryCoverageStatus":"fresh","canonicalHistoryLastScannedBlock":94802620,"canonicalHistoryComparisonBlock":94800081,"canonicalHistoryConsistencyStatus":"match","canonicalHistoryTotalDeltaWei":"111099152860904160","canonicalHistoryAccountCount":3,"canonicalHistoryEventCount":5,"canonicalHistoryHasBorrowAccount":false,"canonicalHistoryHasLegacyUnknownAccount":false,"snapshotYield":"30280348584637","netflowYield":"9996271551029448","diff":"9965991202444811","recentCycleYield":"9996271256448681","recentCycleDiff":"9965990907864044","recentCycleNetFlow":"111099153155484927","resetPar":"219357441","endingPar":"110305575813442922","canonicalHistoryNetflowDiffWei":"0","verificationBaseline":"recent-cycle","preSnapshotCarryYield":"9965990907864044","preSnapshotCarryResidual":"0","preSnapshotCarryWindowType":"exact_post_snapshot_window"},"11":{"token":"0x5b12e419a57e3102ec1d47bd11ba5ec87ef264fb","symbol":"dPT-mETH-26DEC2024","decimals":18,"cumulativeYield":"0","status":"no_netflow","method":"snapshot-only","strictStatus":"coverage_incomplete","strictMethod":"snapshot-only","strictReason":"netflow_missing_market","firstDate":"2026-04-15","firstPar":"99538477286979","firstWei":"99538477286979","lastDate":"2026-05-02","lastPar":"99538477286979","lastWei":"99538477286979","days":18,"isLatestSnapshot":true,"hasStaticParWindow":true,"canonicalHistoryCoverageStatus":"fresh","canonicalHistoryLastScannedBlock":94802620,"canonicalHistoryComparisonBlock":94800081,"canonicalHistoryConsistencyStatus":"none","canonicalHistoryTotalDeltaWei":"0","canonicalHistoryAccountCount":0,"canonicalHistoryEventCount":0,"canonicalHistoryHasBorrowAccount":false,"canonicalHistoryHasLegacyUnknownAccount":false,"snapshotYield":"0"},"15":{"token":"0x8eb2ef96a70a6ec4f3dde550b96969a6aa25a563","symbol":"dPT-cmETH-13FEB2025","decimals":18,"cumulativeYield":"0","status":"no_netflow","method":"snapshot-only","strictStatus":"coverage_incomplete","strictMethod":"snapshot-only","strictReason":"netflow_missing_market","firstDate":"2026-04-15","firstPar":"116540159495158","firstWei":"116540159495158","lastDate":"2026-05-02","lastPar":"116540159495158","lastWei":"116540159495158","days":18,"isLatestSnapshot":true,"hasStaticParWindow":true,"canonicalHistoryCoverageStatus":"fresh","canonicalHistoryLastScannedBlock":94802620,"canonicalHistoryComparisonBlock":94800081,"canonicalHistoryConsistencyStatus":"none","canonicalHistoryTotalDeltaWei":"0","canonicalHistoryAccountCount":0,"canonicalHistoryEventCount":0,"canonicalHistoryHasBorrowAccount":false,"canonicalHistoryHasLegacyUnknownAccount":false,"snapshotYield":"0"}}}