{"version":2,"chain":"mantle","address":"0xd9f4dcfe8732d278529d6b9bb26b47a73e2a8872","snapshotDate":"2026-05-06","generatedAt":"2026-05-06T23:31:57.708296Z","summary":{"verified":0,"pre_snapshot_carry":0,"mismatch":2,"no_netflow":2,"no_snapshot":4,"unavailable":0},"strictSummary":{"verified":0,"inferred":0,"mismatch":2,"coverage_incomplete":6,"unavailable":0},"canonicalHistory":{"coverageStatus":"fresh","lastScannedBlock":94989979,"comparisonBlock":94984052,"freshForNetflowComparison":true},"markets":{"0":{"token":"","symbol":"UNK","decimals":18,"cumulativeYield":"0","status":"no_snapshot","method":"insufficient-history","strictStatus":"coverage_incomplete","strictMethod":"insufficient-history","strictReason":"snapshot_missing_market","firstDate":"","firstPar":"0","firstWei":"0","lastDate":"","lastPar":"0","lastWei":"0","days":0,"isLatestSnapshot":false,"hasStaticParWindow":false,"canonicalHistoryCoverageStatus":"fresh","canonicalHistoryLastScannedBlock":94989979,"canonicalHistoryComparisonBlock":94984052,"canonicalHistoryConsistencyStatus":"match","canonicalHistoryTotalDeltaWei":"-904187569608985","canonicalHistoryAccountCount":4,"canonicalHistoryEventCount":15,"canonicalHistoryHasBorrowAccount":true,"canonicalHistoryHasLegacyUnknownAccount":false,"endingPar":"-865964551378721","canonicalHistoryNetflowDiffWei":"0"},"1":{"token":"0x78c1b0c915c4faa5fffa6cabf0219da63d7f4cb8","symbol":"WMNT","decimals":18,"cumulativeYield":"4209905848032","status":"mismatch","method":"snapshot-fallback","strictStatus":"mismatch","strictMethod":"snapshot-fallback","strictReason":"snapshot_netflow_mismatch","firstDate":"2026-04-15","firstPar":"7872128775945231185","firstWei":"8358165970578430923","lastDate":"2026-05-06","lastPar":"3817031794774894787","lastWei":"4052704223338720981","days":22,"isLatestSnapshot":true,"hasStaticParWindow":false,"canonicalHistoryCoverageStatus":"fresh","canonicalHistoryLastScannedBlock":94989979,"canonicalHistoryComparisonBlock":94984052,"canonicalHistoryConsistencyStatus":"match","canonicalHistoryTotalDeltaWei":"-1297548707767712233","canonicalHistoryAccountCount":10,"canonicalHistoryEventCount":57,"canonicalHistoryHasBorrowAccount":true,"canonicalHistoryHasLegacyUnknownAccount":false,"snapshotYield":"4209905848032","netflowYield":"5350252931106433214","diff":"5350248721200585182","recentCycleYield":"5350250682386445561","recentCycleDiff":"5350246472480597529","recentCycleNetFlow":"-1297546459047724580","resetPar":"146839559292","endingPar":"939057252633466125","canonicalHistoryNetflowDiffWei":"0"},"2":{"token":"","symbol":"UNK","decimals":18,"cumulativeYield":"0","status":"no_snapshot","method":"insufficient-history","strictStatus":"coverage_incomplete","strictMethod":"insufficient-history","strictReason":"snapshot_missing_market","firstDate":"","firstPar":"0","firstWei":"0","lastDate":"","lastPar":"0","lastWei":"0","days":0,"isLatestSnapshot":false,"hasStaticParWindow":false,"canonicalHistoryCoverageStatus":"fresh","canonicalHistoryLastScannedBlock":94989979,"canonicalHistoryComparisonBlock":94984052,"canonicalHistoryConsistencyStatus":"match","canonicalHistoryTotalDeltaWei":"-2172246","canonicalHistoryAccountCount":4,"canonicalHistoryEventCount":11,"canonicalHistoryHasBorrowAccount":true,"canonicalHistoryHasLegacyUnknownAccount":false,"endingPar":"-2027350","canonicalHistoryNetflowDiffWei":"0"},"4":{"token":"","symbol":"UNK","decimals":18,"cumulativeYield":"0","status":"no_snapshot","method":"insufficient-history","strictStatus":"coverage_incomplete","strictMethod":"insufficient-history","strictReason":"snapshot_missing_market","firstDate":"","firstPar":"0","firstWei":"0","lastDate":"","lastPar":"0","lastWei":"0","days":0,"isLatestSnapshot":false,"hasStaticParWindow":false,"canonicalHistoryCoverageStatus":"fresh","canonicalHistoryLastScannedBlock":94989979,"canonicalHistoryComparisonBlock":94984052,"canonicalHistoryConsistencyStatus":"match","canonicalHistoryTotalDeltaWei":"-1627354","canonicalHistoryAccountCount":9,"canonicalHistoryEventCount":43,"canonicalHistoryHasBorrowAccount":true,"canonicalHistoryHasLegacyUnknownAccount":false,"endingPar":"-2242994","canonicalHistoryNetflowDiffWei":"0"},"5":{"token":"0xcda86a272531e8640cd7f1a92c01839911b90bb0","symbol":"mETH","decimals":18,"cumulativeYield":"440563564","status":"mismatch","method":"snapshot-fallback","strictStatus":"mismatch","strictMethod":"snapshot-fallback","strictReason":"snapshot_netflow_mismatch","firstDate":"2026-04-15","firstPar":"1741833834188998","firstWei":"1756439152446509","lastDate":"2026-05-06","lastPar":"522767370433161","lastWei":"527151039246295","days":22,"isLatestSnapshot":true,"hasStaticParWindow":false,"canonicalHistoryCoverageStatus":"fresh","canonicalHistoryLastScannedBlock":94989979,"canonicalHistoryComparisonBlock":94984052,"canonicalHistoryConsistencyStatus":"match","canonicalHistoryTotalDeltaWei":"10967851816632","canonicalHistoryAccountCount":7,"canonicalHistoryEventCount":22,"canonicalHistoryHasBorrowAccount":true,"canonicalHistoryHasLegacyUnknownAccount":false,"snapshotYield":"440563564","netflowYield":"516183187429663","diff":"516182746866099","endingPar":"-15152703447782","canonicalHistoryNetflowDiffWei":"0"},"6":{"token":"","symbol":"UNK","decimals":18,"cumulativeYield":"0","status":"no_snapshot","method":"insufficient-history","strictStatus":"coverage_incomplete","strictMethod":"insufficient-history","strictReason":"snapshot_missing_market","firstDate":"","firstPar":"0","firstWei":"0","lastDate":"","lastPar":"0","lastWei":"0","days":0,"isLatestSnapshot":false,"hasStaticParWindow":false,"canonicalHistoryCoverageStatus":"fresh","canonicalHistoryLastScannedBlock":94989979,"canonicalHistoryComparisonBlock":94984052,"canonicalHistoryConsistencyStatus":"match","canonicalHistoryTotalDeltaWei":"-103830953841474","canonicalHistoryAccountCount":2,"canonicalHistoryEventCount":4,"canonicalHistoryHasBorrowAccount":false,"canonicalHistoryHasLegacyUnknownAccount":false,"endingPar":"0","canonicalHistoryNetflowDiffWei":"0"},"7":{"token":"0xb3ff983d7927540b7f92602657a2a26977664e77","symbol":"dPT-USDe-25JUL2024","decimals":18,"cumulativeYield":"0","status":"no_netflow","method":"snapshot-only","strictStatus":"coverage_incomplete","strictMethod":"snapshot-only","strictReason":"netflow_missing_market","firstDate":"2026-04-15","firstPar":"1343818774358225813","firstWei":"1343818774358225813","lastDate":"2026-05-06","lastPar":"1343818774358225813","lastWei":"1343818774358225813","days":22,"isLatestSnapshot":true,"hasStaticParWindow":true,"canonicalHistoryCoverageStatus":"fresh","canonicalHistoryLastScannedBlock":94989979,"canonicalHistoryComparisonBlock":94984052,"canonicalHistoryConsistencyStatus":"none","canonicalHistoryTotalDeltaWei":"0","canonicalHistoryAccountCount":0,"canonicalHistoryEventCount":0,"canonicalHistoryHasBorrowAccount":false,"canonicalHistoryHasLegacyUnknownAccount":false,"snapshotYield":"0"},"12":{"token":"0xe44cefd2e6b0b846e2720e7b823e173d9fdf8601","symbol":"dPT-sMNT-3OCT2024","decimals":18,"cumulativeYield":"0","status":"no_netflow","method":"snapshot-only","strictStatus":"coverage_incomplete","strictMethod":"snapshot-only","strictReason":"netflow_missing_market","firstDate":"2026-04-15","firstPar":"814750734132895","firstWei":"814750734132895","lastDate":"2026-05-06","lastPar":"814750734132895","lastWei":"814750734132895","days":22,"isLatestSnapshot":true,"hasStaticParWindow":true,"canonicalHistoryCoverageStatus":"fresh","canonicalHistoryLastScannedBlock":94989979,"canonicalHistoryComparisonBlock":94984052,"canonicalHistoryConsistencyStatus":"none","canonicalHistoryTotalDeltaWei":"0","canonicalHistoryAccountCount":0,"canonicalHistoryEventCount":0,"canonicalHistoryHasBorrowAccount":false,"canonicalHistoryHasLegacyUnknownAccount":false,"snapshotYield":"0"}}}